hypixelapi/__init__.py
hypixelapi/exceptions.py
hypixelapi/hypixelapi.py
hypixelapi/util/__init__.py
hypixelapi/util/game_type.py
hypixelapi/util/general.py
hypixelapi/util/mojang.py
hypixelapi/util/validator.py
pyhypixel-1.2.0.dist-info/LICENSE
pyhypixel-1.2.0.dist-info/METADATA
pyhypixel-1.2.0.dist-info/WHEEL
pyhypixel-1.2.0.dist-info/top_level.txt
pyhypixel-1.2.0.dist-info/RECORD
