Metadata-Version: 2.1
Name: pyhypixel
Version: 1.2.0
Summary: An unofficial HypixelAPI wrapper
Home-page: https://github.com/xMicky24GIT/pyhypixel
Author: SonoMichele
Author-email: micheleviotto@protonmail.com
License: UNKNOWN
Platform: UNKNOWN
Classifier: Programming Language :: Python :: 3
Classifier: License :: OSI Approved :: GNU General Public License v3 (GPLv3)
Classifier: Operating System :: OS Independent
Requires-Dist: requests
